{
  "debug": true,
  "logfile": "",
  "thread_sleep": 0.5,
  "concurrency_num": 1,
  "batch": 98,
  "puller": {
    "queue_suffix": "monitor_queue_storage",
    "backend_type": "storage",
    "connection_params": {
        "type": "redis",
        "host": "localhost",
        "port": 6379,
        "db": 0
    }
  },
  "database": {
    "type": "mongodb",
    "host": "127.0.0.1",
    "port": 27017,
    "user": "ease_monitor",
    "name": "ease_monitor",
    "password": "ease_monitor_pass",
    "document_name": "monitor_data"
  }
}
