{
    "debug": false,
    "logfile": "/home/easemonitor/log/storage.log",
    "node_name": "store-00",
    "thread_sleep": 0.5,
    "concurrency_num": 1,
    "queue": {
      "enabled": true,
      "type": "redis",
      "queue_suffix": "monitor_queue",
      "batch": 1000,
      "addr": {
        "host": "localhost",
        "port": 6379,
        "db": 0
      }
    },
    "database": {
      "enabled": true,
      "type": "mongodb",
      "host": "10.83.3.46",
      "port": 30000,
      "user": "easy_monitor",
      "db_name": "easy_monitor",
      "document_name": "monitor_60"
    }
}
